tf_q_finance-0.0.1.dev35.dist-info/licenses/LICENSE
tf_quant_finance/__init__.py
tf_quant_finance/black_scholes/__init__.py
tf_quant_finance/black_scholes/asian_prices.py
tf_quant_finance/black_scholes/brownian_bridge.py
tf_quant_finance/black_scholes/crr_binomial_tree.py
tf_quant_finance/black_scholes/implied_vol_approximation.py
tf_quant_finance/black_scholes/implied_vol_lib.py
tf_quant_finance/black_scholes/implied_vol_newton_root.py
tf_quant_finance/black_scholes/implied_vol_utils.py
tf_quant_finance/black_scholes/vanilla_prices.py
tf_quant_finance/black_scholes/variance_swaps.py
tf_quant_finance/black_scholes/approximations/__init__.py
tf_quant_finance/black_scholes/approximations/american_option.py
tf_quant_finance/datetime/__init__.py
tf_quant_finance/datetime/bounded_holiday_calendar.py
tf_quant_finance/datetime/constants.py
tf_quant_finance/datetime/date_tensor.py
tf_quant_finance/datetime/date_utils.py
tf_quant_finance/datetime/daycounts.py
tf_quant_finance/datetime/holiday_calendar.py
tf_quant_finance/datetime/holiday_calendar_factory.py
tf_quant_finance/datetime/holiday_utils.py
tf_quant_finance/datetime/schedules.py
tf_quant_finance/datetime/tensor_wrapper.py
tf_quant_finance/datetime/unbounded_holiday_calendar.py
tf_quant_finance/datetime/periods/__init__.py
tf_quant_finance/datetime/periods/period_tensors.py
tf_quant_finance/examples/demos/option_pricing_basic/common/__init__.py
tf_quant_finance/examples/demos/option_pricing_basic/common/datatypes.py
tf_quant_finance/examples/demos/option_pricing_basic/data_generator/data_generation.py
tf_quant_finance/examples/demos/option_pricing_basic/downloader/app/main.py
tf_quant_finance/examples/demos/option_pricing_basic/pricer/app/main.py
tf_quant_finance/examples/demos/option_pricing_basic/pricer/app/pricers.py
tf_quant_finance/experimental/__init__.py
tf_quant_finance/experimental/io.py
tf_quant_finance/experimental/american_option_pricing/__init__.py
tf_quant_finance/experimental/american_option_pricing/andersen_lake.py
tf_q_finance-0.0.1.dev35.dist-info/METADATA
tf_q_finance-0.0.1.dev35.dist-info/WHEEL
tf_q_finance-0.0.1.dev35.dist-info/top_level.txt
tf_q_finance-0.0.1.dev35.dist-info/RECORD
