Metadata-Version: 2.4
Name: tf-q-finance
Version: 0.0.1.dev35
Summary: High-performance TensorFlow library for quantitative finance.
Home-page: https://github.com/paolodelia99/tf-quant-finance
Author: Google Inc.
Author-email: "Google Inc." <tf-quant-finance@google.com>, Paolo D'Elia <paolo.delia99@gmail.com>
License-Expression: Apache-2.0
Project-URL: Homepage, https://github.com/paolodelia99/tf-quant-finance
Project-URL: Repository, https://github.com/paolodelia99/tf-quant-finance
Keywords: tensorflow,quantitative,finance,hpc,gpu,option,pricing
Classifier: Development Status :: 2 - Pre-Alpha
Classifier: Intended Audience :: Developers
Classifier: Intended Audience :: Education
Classifier: Intended Audience :: Financial and Insurance Industry
Classifier: Programming Language :: Python :: 3.9
Classifier: Programming Language :: Python :: 3.10
Classifier: Programming Language :: Python :: 3.11
Classifier: Programming Language :: Python :: 3.12
Classifier: Natural Language :: English
Classifier: Topic :: Scientific/Engineering :: Mathematics
Classifier: Topic :: Software Development :: Libraries :: Python Modules
Classifier: Topic :: Software Development :: Libraries
Classifier: Operating System :: OS Independent
Requires-Python: >=3.9
License-File: LICENSE
Requires-Dist: attrs==25.3.0
Requires-Dist: tensorflow-probability==0.25.0
Requires-Dist: numpy>=2.0.2
Requires-Dist: protobuf==5.29.5
Dynamic: author
Dynamic: home-page
Dynamic: license-file
